rom.sv
module rom #(
    parameter ADDRESS_WIDTH=8,
              DATA_WIDTH=32
)(
    input logic [DATA_WIDTH-1:0]         PC,
    output logic [DATA_WIDTH-1:0]           instr
);

logic [DATA_WIDTH-1:0] rom_array [2**ADDRESS_WIDTH-1:0];

assign instr = rom_array[PC[DATA_WIDTH-1:2]];

initial begin
        $display("Loading rom.");
        $readmemh("main.mem",rom_array);
end;
//asynchronous memory therefore not dependant on clk or rst

endmodule

src/PC_mod.sv
module PC_mod#(
    parameter WIDTH=32
    
)(
        //interface signals
    input  logic             clk,      // clock 
    input  logic             rst,      // reset
    input  logic             PC_CTRL,      // Program counter control (from control unit, do we branch or move to the next address, ie pc=pc+imm or pc=pc+4)
    input  logic [WIDTH-1:0]   ImmOp,  //Immediate value to add to current PC val
    output  logic [WIDTH-1:0]   PC_curr  //next pc after next clk cycle (prev clk if no in next clk cycle)
);

/* Tried to do soemthign like this but it didn't work propebaly have to use
* a always comb sstatement to do this
logic [WIDTH-1:0] branch_PC= PC + ImmOp;
logic [WIDTH-1:0] incr_PC= PC + 3'b100;
logic [WIDTH-1:0] next_PC= PC_CTRL ? branch_PC : incr_PC ;
*/

logic [WIDTH-1:0] next_PC ;

always_ff @(posedge clk) begin
    if(rst)
        PC_curr <= 0;
    else
        next_PC <= PC_CTRL ? PC_curr + ImmOp : PC_curr + 3'b100 ; PC_curr<= next_PC;
    end
endmodule

src/top.sv
module top#(
    parameter WIDTH=32
)(
        //interface signals
    input  logic             clk,      // clock 
    input  logic             rst,      // reset
    input  logic             PC_CTRL,      // Program counter control (from control unit, do we branch or move to the next address, ie pc=pc+imm or pc=pc+4)
    input  logic [WIDTH-1:0]   ImmOp,  //Immediate value to add to current PC val
    output  logic [WIDTH-1:0]   dout  //current instruction
);

logic [WIDTH-1:0] addr;

PC_mod PC (
    .clk(clk),
    .rst(rst),
    .PC_CTRL(PC_CTRL),
    .ImmOp(ImmOp),
    .PC_curr(addr)
);

rom Rom(
    .PC(addr),
    .instr(dout)
);

endmodule

Vtop2.vcd
$version Generated by VerilatedVcd $end
$timescale 1ps $end

 $scope module TOP $end
  $var wire 32 & ImmOp [31:0] $end
  $var wire  1 % PC_CTRL $end
  $var wire  1 # clk $end
  $var wire 32 ' dout [31:0] $end
  $var wire  1 $ rst $end
  $scope module top $end
   $var wire 32 & ImmOp [31:0] $end
   $var wire  1 % PC_CTRL $end
   $var wire 32 * WIDTH [31:0] $end
   $var wire 32 ( addr [31:0] $end
   $var wire  1 # clk $end
   $var wire 32 ' dout [31:0] $end
   $var wire  1 $ rst $end
   $scope module PC $end
    $var wire 32 & ImmOp [31:0] $end
    $var wire  1 % PC_CTRL $end
    $var wire 32 ( PC_curr [31:0] $end
    $var wire 32 * WIDTH [31:0] $end
    $var wire  1 # clk $end
    $var wire 32 ) next_PC [31:0] $end
    $var wire  1 $ rst $end
   $upscope $end
   $scope module Rom $end
    $var wire 32 + ADDRESS_WIDTH [31:0] $end
    $var wire 32 * DATA_WIDTH [31:0] $end
    $var wire 32 ( PC [31:0] $end
    $var wire 32 ' instr [31:0] $end
   $upscope $end
  $upscope $end
 $upscope $end
$enddefinitions $end


#0
1#
0$
1%
b00000000000000000000000000000100 &
b00000000000000000000000000000000 '
b00000000000000000000000000000000 (
b00000000000000000000000000000000 )
b00000000000000000000000000100000 *
b00000000000000000000000000001000 +
#1
0#
b11111110111111011111110111111101 '
#2
1#
b00000000000000000000000000000100 )
#3
0#
#4
1#
b11110100111100111111000111110000 '
b00000000000000000000000000000100 (
#5
0#
#6
1#
b00000000000000000000000000001000 )
#7
0#
#8
1#
b11011000110101101101010011010001 '
b00000000000000000000000000001000 (
#9
0#
#10
1#
b00000000000000000000000000001100 )
#11
0#
#12
1#
b10101111101011001010100110100110 '
b00000000000000000000000000001100 (
#13
0#
#14
1#
b00000000000000000000000000010000 )
#15
0#
#16
1#
b01111110011110110111100001110101 '
b00000000000000000000000000010000 (
#17
0#
#18
1#
b00000000000000000000000000010100 )
#19
0#
#20
1#
b01001110010010110100100001000101 '
b00000000000000000000000000010100 (
#21
0#
#22
1#
b00000000000000000000000000011000 )
#23
0#
#24
1#
b00100101001000110010000000011110 '
b00000000000000000000000000011000 (
#25
0#
#26
1#
b00000000000000000000000000011100 )
#27
0#
#28
1#
b00001001000010000000011100000110 '
b00000000000000000000000000011100 (
#29
0#
#30
1#
b00000000000000000000000000100000 )
#31
0#
#32
1#
b00000000000000000000000000000000 '
b00000000000000000000000000100000 (
#33
0#
#34
1#
b00000000000000000000000000100100 )
#35
0#
#36
1#
b00001001000010100000110000001101 '
b00000000000000000000000000100100 (
#37
0#
#38
1#
b00000000000000000000000000101000 )
#39
0#
#40
1#
b00100101001001110010100100101100 '
b00000000000000000000000000101000 (
#41
0#
#42
1#
b00000000000000000000000000101100 )
#43
0#
#44
1#
b01001110010100010101010001010111 '
b00000000000000000000000000101100 (
#45
0#
#46
1#
b00000000000000000000000000110000 )
#47
0#
#48
1#
b01111111100000101000010110001000 '
b00000000000000000000000000110000 (
#49
0#
#50
1#
b00000000000000000000000000110100 )
#51
0#
#52
1#
b10101111101100101011010110111000 '
b00000000000000000000000000110100 (
#53
0#
#54
1#
b00000000000000000000000000111000 )
#55
0#
#56
1#
b11011000110110101101110111011111 '
b00000000000000000000000000111000 (
#57
0#
#58
1#
b00000000000000000000000000111100 )
#59
0#
#60
1#
b11110100111101011111011011110111 '
b00000000000000000000000000111100 (
#61
0#
#62
1#
b00000000000000000000000001000000 )
#63
0#
#64
1#
b11111110111111011111110111111101 '
b00000000000000000000000001000000 (
#65
0#
#66
1#
b00000000000000000000000001000100 )
#67
0#
#68
1#
b11110100111100111111000111110000 '
b00000000000000000000000001000100 (
#69
0#
#70
1#
b00000000000000000000000001001000 )
#71
0#
#72
1#
b11011000110101101101010011010001 '
b00000000000000000000000001001000 (
#73
0#
#74
1#
b00000000000000000000000001001100 )
#75
0#
#76
1#
b00000000000000000000000000000000 '
b00000000000000000000000001001100 (
#77
0#
#78
1#
b00000000000000000000000001010000 )
