src/rom.sv
module rom #(
    parameter NUM_ADDRESSES=10, //we have 2^10 memory locations (addresses)
              PC_WIDTH=32, //our program counter is 32 bits
              DATA_WIDTH=8,//byte adressing and so each adresss holds data of width 8 bits
              INSTRUCTION_WIDTH=32 //width of our instruction
)(
    input logic [PC_WIDTH-1:0]         PC, //current program counter
    output logic [INSTRUCTION_WIDTH-1:0]           instr //the instruction at this PC value
);

logic [DATA_WIDTH-1:0] rom_array [2**NUM_ADDRESSES-1:0]; /* allocate a rom array (only should read instruction mem and never write to it so we dont use RAM) 
of size 8 bits in each mem location, and we have 2^10 of these  8 bit locations (same as having 2^8=256 32 bit memory locations)*/

//ignore the last 2 bits of our pc, since we need to make this byte addressed
logic   [PC_WIDTH-1:0]   addr = {PC[31:2], 2'b0};

/*Byte addressing - Each instruction is made of 4 addresses, and these
addresses are offsets of the addr value, where we offset by values:
- 0 : byte 0
- 1 : byte 1
- 2 : byte 2
- 3 : byte 3

and through the concatination of these bytes, we reconstruct our original instruction
*/

//The memory file is read from left to right, and so the byte of offset 0 (byte 1) corrosponds ot the MSB and the byte of offset 3 (byte 4) is the LSB
assign instr = {rom_array[addr],rom_array[addr+1], rom_array[addr+2],rom_array[addr+3]};


initial begin
        $display("Loading rom.");
        $readmemh("main.mem",rom_array);
end;
//asynchronous memory therefore not dependant on clk or rst

endmodule

src/PC_mod.sv
module PC_mod#(
    parameter WIDTH=32
    
)(
        //interface signals
    input  logic             clk,      // clock 
    input  logic             rst,      // reset
    input  logic             PC_CTRL,      // Program counter control (from control unit, do we branch or move to the next address, ie pc=pc+imm or pc=pc+4)
    input  logic [WIDTH-1:0]   ImmOp,  //Immediate value to add to current PC val
    output  logic [WIDTH-1:0]   PC_curr  //next pc after next clk cycle (prev clk if no in next clk cycle)
);

// Insures that in the beginning our PC value is 0 in beginning, preventing undefined behaviour

initial 
    PC_curr = 0;

always_ff @(posedge clk) 
    
    if(rst) PC_curr <= 0;    
    //mux selecting immop if PC_CTRL=1 or adds current PC by 4 if not
    else PC_curr <= PC_CTRL ? PC_curr + ImmOp : PC_curr + 4 ;

endmodule

src/top.sv
module top#(
    parameter WIDTH=32
)(
        //interface signals
    input  logic             clk,      // clock 
    input  logic             rst,      // reset
    input  logic             PC_CTRL,      // Program counter control (from control unit, do we branch or move to the next address, ie pc=pc+imm or pc=pc+4)
    input  logic [WIDTH-1:0]   ImmOp,  //Immediate value to add to current PC val
    output  logic [WIDTH-1:0]   dout  //current instruction
);

logic [WIDTH-1:0] addr;

PC_mod PC (
    .clk(clk),
    .rst(rst),
    .PC_CTRL(PC_CTRL),
    .ImmOp(ImmOp),
    .PC_curr(addr)
);

rom Rom(
    .PC(addr),
    .instr(dout)
);

endmodule

src/Vtop.vcd
$version Generated by VerilatedVcd $end
$timescale 1ps $end

 $scope module TOP $end
  $var wire 32 & ImmOp [31:0] $end
  $var wire  1 % PC_CTRL $end
  $var wire  1 # clk $end
  $var wire 32 ' dout [31:0] $end
  $var wire  1 $ rst $end
  $scope module top $end
   $var wire 32 & ImmOp [31:0] $end
   $var wire  1 % PC_CTRL $end
   $var wire 32 * WIDTH [31:0] $end
   $var wire 32 ( addr [31:0] $end
   $var wire  1 # clk $end
   $var wire 32 ' dout [31:0] $end
   $var wire  1 $ rst $end
   $scope module PC $end
    $var wire 32 & ImmOp [31:0] $end
    $var wire  1 % PC_CTRL $end
    $var wire 32 ( PC_curr [31:0] $end
    $var wire 32 * WIDTH [31:0] $end
    $var wire  1 # clk $end
    $var wire  1 $ rst $end
   $upscope $end
   $scope module Rom $end
    $var wire 32 , DATA_WIDTH [31:0] $end
    $var wire 32 * INSTRUCTION_WIDTH [31:0] $end
    $var wire 32 + NUM_ADDRESSES [31:0] $end
    $var wire 32 ( PC [31:0] $end
    $var wire 32 * PC_WIDTH [31:0] $end
    $var wire 32 ) addr [31:0] $end
    $var wire 32 ' instr [31:0] $end
   $upscope $end
  $upscope $end
 $upscope $end
$enddefinitions $end


#0
0#
0$
1%
b00000000000000000000000000000100 &
b00000000000000000000000000000000 '
b00000000000000000000000000000000 (
b00000000000000000000000000000000 )
b00000000000000000000000000100000 *
b00000000000000000000000000001010 +
b00000000000000000000000000001000 ,
#1
1#
b11111110111111011111110111111101 '
#2
0#
#3
1#
b11110100111100111111000111110000 '
b00000000000000000000000000000100 (
b00000000000000000000000000000100 )
#4
0#
#5
1#
b11011000110101101101010011010001 '
b00000000000000000000000000001000 (
b00000000000000000000000000001000 )
#6
0#
#7
1#
b10101111101011001010100110100110 '
b00000000000000000000000000001100 (
b00000000000000000000000000001100 )
#8
0#
#9
1#
b01111110011110110111100001110101 '
b00000000000000000000000000010000 (
b00000000000000000000000000010000 )
#10
0#
#11
1#
b01001110010010110100100001000101 '
b00000000000000000000000000010100 (
b00000000000000000000000000010100 )
#12
0#
#13
1#
b00100101001000110010000000011110 '
b00000000000000000000000000011000 (
b00000000000000000000000000011000 )
#14
0#
#15
1#
b00001001000010000000011100000110 '
b00000000000000000000000000011100 (
b00000000000000000000000000011100 )
#16
0#
#17
1#
b00000000000000000000000000000000 '
b00000000000000000000000000100000 (
b00000000000000000000000000100000 )
#18
0#
#19
1#
b00001001000010100000110000001101 '
b00000000000000000000000000100100 (
b00000000000000000000000000100100 )
#20
0#
#21
1#
b00100101001001110010100100101100 '
b00000000000000000000000000101000 (
b00000000000000000000000000101000 )
#22
0#
#23
1#
b01001110010100010101010001010111 '
b00000000000000000000000000101100 (
b00000000000000000000000000101100 )
#24
0#
#25
1#
b01111111100000101000010110001000 '
b00000000000000000000000000110000 (
b00000000000000000000000000110000 )
#26
0#
#27
1#
b10101111101100101011010110111000 '
b00000000000000000000000000110100 (
b00000000000000000000000000110100 )
#28
0#
#29
1#
b11011000110110101101110111011111 '
b00000000000000000000000000111000 (
b00000000000000000000000000111000 )
#30
0#
#31
1#
b11110100111101011111011011110111 '
b00000000000000000000000000111100 (
b00000000000000000000000000111100 )
#32
0#
#33
1#
b11111110111111011111110111111101 '
b00000000000000000000000001000000 (
b00000000000000000000000001000000 )
#34
0#
#35
1#
b11110100111100111111000111110000 '
b00000000000000000000000001000100 (
b00000000000000000000000001000100 )
#36
0#
#37
1#
b11011000110101101101010011010001 '
b00000000000000000000000001001000 (
b00000000000000000000000001001000 )
#38
0#
#39
1#
b00000000000000000000000000000000 '
b00000000000000000000000001001100 (
b00000000000000000000000001001100 )
#40
0#
#41
1#
b00000000000000000000000001010000 (
b00000000000000000000000001010000 )
#42
0#
#43
1#
b00000000000000000000000001010100 (
b00000000000000000000000001010100 )
#44
0#
#45
1#
b00000000000000000000000001011000 (
b00000000000000000000000001011000 )
#46
0#
#47
1#
b00000000000000000000000001011100 (
b00000000000000000000000001011100 )
#48
0#
#49
1#
b00000000000000000000000001100000 (
b00000000000000000000000001100000 )
#50
0#
#51
1#
b00000000000000000000000001100100 (
b00000000000000000000000001100100 )
#52
0#
#53
1#
b00000000000000000000000001101000 (
b00000000000000000000000001101000 )
#54
0#
#55
1#
b00000000000000000000000001101100 (
b00000000000000000000000001101100 )
#56
0#
#57
1#
b00000000000000000000000001110000 (
b00000000000000000000000001110000 )
#58
0#
#59
1#
b00000000000000000000000001110100 (
b00000000000000000000000001110100 )
#60
0#
#61
1#
b00000000000000000000000001111000 (
b00000000000000000000000001111000 )
#62
0#
#63
1#
b00000000000000000000000001111100 (
b00000000000000000000000001111100 )
#64
0#
#65
1#
b00000000000000000000000010000000 (
b00000000000000000000000010000000 )
#66
0#
#67
1#
b00000000000000000000000010000100 (
b00000000000000000000000010000100 )
#68
0#
#69
1#
b00000000000000000000000010001000 (
b00000000000000000000000010001000 )
#70
0#
#71
1#
b00000000000000000000000010001100 (
b00000000000000000000000010001100 )
#72
0#
#73
1#
b00000000000000000000000010010000 (
b00000000000000000000000010010000 )
#74
0#
#75
1#
b00000000000000000000000010010100 (
b00000000000000000000000010010100 )
#76
0#
#77
1#
b00000000000000000000000010011000 (
b00000000000000000000000010011000 )
#78
0#
#79
1#
b00000000000000000000000010011100 (
b00000000000000000000000010011100 )
